{"Washington, DC, USA": ["pl-0ad7fcb8ef752c6bf"], "Columbus, OH, USA": ["pl-03de0f388e150b7a0"], "San Francisco, CA, USA": ["pl-058fdfd02288059aa"], "Portland, OR, USA": ["pl-028ae6d7cb9499d16"], "Montreal, Qu\u00c3\u00a9bec, CA": ["pl-0be55eeaab7c0f70d"], "Dublin, IE": ["pl-0488844575792fc6e"], "London, England, UK": ["pl-00fe1daa39189555e"], "Paris, FR": ["pl-04046b13618d7a15b"], "Frankfurt, DE": ["pl-0f7b226fa7566a39b"], "Stockholm, SE": ["pl-04aeaeb6baaf95b64"], "Milan, IT": ["pl-00b3852572b8ae3e9"], "Tokyo, JP": ["pl-01da6f448837acc82"], "Seoul, KR": ["pl-031c4da5b922c7d67"], "Singapore, SG": ["pl-0a703993a98f25f0d"], "Sydney, AU": ["pl-048ee3c15e3b23943"], "Mumbai, IN": ["pl-00171e5cf14465825"], "Hong Kong, HK": ["pl-0d9d31a572c4dff24"], "S\u00c3\u00a3o Paulo, BR": ["pl-0440edee3e40052f6"], "Manama, BH": ["pl-03d88dece65ee986c"], "Cape Town, ZA": ["pl-0beb7c24ce908c7df"]}